{"/about":"pages/about.html","/contact":"pages/contact.html","/":"pages/index.html","/portfolio":"pages/portfolio.html","/services":"pages/services.html","/services/custom-installations":"pages/services/custom-installations.html","/services/energy-management":"pages/services/energy-management.html","/services/home-automation":"pages/services/home-automation.html","/services/security-systems":"pages/services/security-systems.html","/support":"pages/support.html","/support/getting-started":"pages/support/getting-started.html","/support/home-automation":"pages/support/home-automation.html","/support/security-systems":"pages/support/security-systems.html","/_app":"pages/_app.js","/_error":"pages/_error.js","/_document":"pages/_document.js","/404":"pages/404.html"}